library_management_system/__init__.py
library_management_system/main.py
JoelAntony_LibraryManager_BPS_Doha-2.0.0.dist-info/METADATA
JoelAntony_LibraryManager_BPS_Doha-2.0.0.dist-info/WHEEL
JoelAntony_LibraryManager_BPS_Doha-2.0.0.dist-info/top_level.txt
JoelAntony_LibraryManager_BPS_Doha-2.0.0.dist-info/RECORD
