Metadata-Version: 2.1
Name: JoelAntony_LibraryManager_BPS_Doha
Version: 2.0.0
Summary: A tool for managing library operations such as book registration, issuance, and return with a Tkinter-based GUI for an enhanced user experience.
Home-page: 
Author: Joel Varghese Antony
Author-email: joelantony30101@gmail.com
Classifier: Programming Language :: Python :: 3
Classifier: License :: OSI Approved :: MIT License
Classifier: Operating System :: OS Independent
Requires-Python: >=3.6
